moveread/models/__init__.py
moveread/models/__init__.pyi
moveread/models/api.py
moveread/models/impl/__init__.py
moveread/models/impl/__init__.pyi
moveread/models/impl/_optimizer.py
moveread/models/impl/eval.py
moveread/models/impl/models/__init__.py
moveread/models/impl/models/__init__.pyi
moveread/models/impl/models/_load.py
moveread/models/impl/models/_original.py
moveread/models/impl/models/create.py
moveread/models/types/__init__.py
moveread/models/types/__init__.pyi
moveread/models/types/_types.py
moveread/models/types/hparams/__init__.py
moveread/models/types/hparams/__init__.pyi
moveread/models/types/hparams/_hparams.py
moveread/models/types/hparams/models.py
moveread/models/types/hparams/optimizers.py
moveread/models/types/hparams/run.py
moveread_models-0.1.3.dist-info/METADATA
moveread_models-0.1.3.dist-info/WHEEL
moveread_models-0.1.3.dist-info/top_level.txt
moveread_models-0.1.3.dist-info/RECORD
